mlb_data_ingest/MLBDataIngestor.py
mlb_data_ingest/__init__.py
mlb_data_ingest/tests/__init__.py
mlb_data_ingest/tests/test_MLBDataIngestor.py
mlb_data_ingest-0.1.0.dist-info/METADATA
mlb_data_ingest-0.1.0.dist-info/WHEEL
mlb_data_ingest-0.1.0.dist-info/top_level.txt
mlb_data_ingest-0.1.0.dist-info/RECORD
